.gitignore
CHANGES.rst
MANIFEST.in
README.rst
setup.cfg
setup.py
docs/.gitignore
docs/Makefile
docs/api.rst
docs/conf.py
docs/glossary.rst
docs/index.rst
khufu_traversal/__init__.py
khufu_traversal/_api.py
khufu_traversal/demo.py
khufu_traversal/tests.py
khufu_traversal.egg-info/PKG-INFO
khufu_traversal.egg-info/SOURCES.txt
khufu_traversal.egg-info/dependency_links.txt
khufu_traversal.egg-info/not-zip-safe
khufu_traversal.egg-info/requires.txt
khufu_traversal.egg-info/top_level.txt