Metadata-Version: 1.0
Name: khufu-traversal
Version: 1.0a1
Summary: Helper for working with SQL-based traversal in Pyramid
Home-page: http://khufuproject.github.com/khufu_traveral/
Author: Rocky Burt
Author-email: rocky@serverzen.com
License: BSD
Keywords: web wsgi pylons pyramid sql traversal
Platform: UNKNOWN
Classifier: License :: OSI Approved :: BSD License
Classifier: Development Status :: 3 - Alpha
Classifier: Programming Language :: Python
